hydronet/__init__.py
hydronet/cli.py
hydronet/simple_predictor.py
hydronet/extended/__init__.py
hydronet/extended/hydro_metrics.py
hydronet/extended/monitor.py
hydronet/extended/predictor.py
hydronet-1.0.0.dist-info/licenses/AUTHORS.md
hydronet-1.0.0.dist-info/licenses/LICENSE
hydronet-1.0.0.dist-info/METADATA
hydronet-1.0.0.dist-info/WHEEL
hydronet-1.0.0.dist-info/top_level.txt
hydronet-1.0.0.dist-info/RECORD
