Metadata-Version: 2.4
Name: hydronet
Version: 1.0.0
Summary: Network-Based Early Warning System for Hydrological Collapse
Author: Samir Baladi
Author-email: Samir Baladi <emerladcompass@gmail.com>
License: MIT
Keywords: hydrology,network-analysis,early-warning,groundwater
Requires-Python: >=3.8
License-File: LICENSE
License-File: AUTHORS.md
Provides-Extra: dev
Requires-Dist: pytest; extra == "dev"
Requires-Dist: black; extra == "dev"
Requires-Dist: flake8; extra == "dev"
Requires-Dist: mypy; extra == "dev"
Provides-Extra: docs
Requires-Dist: sphinx; extra == "docs"
Requires-Dist: sphinx-rtd-theme; extra == "docs"
Dynamic: author
Dynamic: license-file
Dynamic: requires-python
